resourceful/__init__.py
resourceful/py.typed
resourceful/resource_manager.py
resourceful/pygame/__init__.py
resourceful/pygame/pygame_prebuilt.py
simply_resourceful-1.0.0.dist-info/LICENSE
simply_resourceful-1.0.0.dist-info/METADATA
simply_resourceful-1.0.0.dist-info/WHEEL
simply_resourceful-1.0.0.dist-info/top_level.txt
simply_resourceful-1.0.0.dist-info/RECORD
