Metadata-Version: 2.1
Name: simply_resourceful
Version: 1.0.0
Summary: A lazy-loading resource manager, especially for use with pygame-ce
Author-email: BetterBuiltFool <betterbuiltfool@gmail.com>
Classifier: Programming Language :: Python :: 3
Classifier: License :: OSI Approved :: MIT License
Classifier: Operating System :: OS Independent
Classifier: Topic :: Games/Entertainment
Classifier: Topic :: Software Development :: Libraries :: pygame
Classifier: Typing :: Typed
Requires-Python: >=3.12.4
License-File: LICENSE
Provides-Extra: test
Requires-Dist: pyfakefs>=5.7.3; extra == "test"
Provides-Extra: pygame
Requires-Dist: pygame_ce>=2.5.2; extra == "pygame"
